geocoding/__init__.py
geocoding/__main__.py
geocoding/activate_reverse.py
geocoding/ban_processing.py
geocoding/datapaths.py
geocoding/datatypes.py
geocoding/distance.py
geocoding/download.py
geocoding/index.py
geocoding/normalize.py
geocoding/query.py
geocoding/result.py
geocoding/search.py
geocoding/similarity.py
geocoding/utils.py
Geocoding-1.4.3.dist-info/LICENSE
Geocoding-1.4.3.dist-info/METADATA
Geocoding-1.4.3.dist-info/WHEEL
Geocoding-1.4.3.dist-info/entry_points.txt
Geocoding-1.4.3.dist-info/top_level.txt
Geocoding-1.4.3.dist-info/RECORD
