Metadata-Version: 2.1
Name: Geocoding
Version: 1.4.3
Summary: geocoding is an address search engine for France
Home-page: https://github.com/DeVilhena-Paulo/Geocoding
Author: Paulo Emilio de Vilhena
Author-email: pevilhena2@gmail.com
License: Apache Software License
Keywords: Geocoder France
Platform: UNKNOWN
Classifier: Development Status :: 3 - Alpha
Classifier: Intended Audience :: Financial and Insurance Industry
Classifier: Topic :: Utilities
Classifier: License :: OSI Approved :: Apache Software License
Classifier: Programming Language :: Python :: 3
Classifier: Programming Language :: Python :: 3.3
Classifier: Programming Language :: Python :: 3.4
Classifier: Programming Language :: Python :: 3.5
Classifier: Programming Language :: Python :: 3.6
Classifier: Programming Language :: Python :: 3.7
Requires-Dist: numpy
Requires-Dist: Unidecode
Requires-Dist: KdQuery
Requires-Dist: sortedcontainers
Requires-Dist: requests
